RL_OM/MLtools.py
RL_OM/__init__.py
RL_OM/_modidx 2.py
RL_OM/_modidx 3.py
RL_OM/_modidx.py
RL_OM/core.py
RL_OM/utils.py
RL_OM/agents/__init__.py
RL_OM/agents/benchmark_agents/PPO_SB3.py
RL_OM/agents/benchmark_agents/PPO_TEMP.py
RL_OM/agents/benchmark_agents/__init__.py
RL_OM/agents/benchmark_agents/cbs.py
RL_OM/agents/benchmark_agents/dual_sourcing.py
RL_OM/agents/benchmark_agents/eoq.py
RL_OM/agents/benchmark_agents/mp_agents_ERM.py
RL_OM/agents/benchmark_agents/nv_agents.py
RL_OM/agents/benchmark_agents/nv_agents_ERM.py
RL_OM/agents/benchmark_agents/nv_agents_SAA.py
RL_OM/agents/benchmark_agents/nv_agents_gradient_boosting.py
RL_OM/agents/benchmark_agents/qr.py
RL_OM/agents/benchmark_agents/saa.py
RL_OM/agents/benchmark_agents/ss.py
RL_OM/agents/networks/__init__.py
RL_OM/agents/networks/actors.py
RL_OM/agents/networks/base.py
RL_OM/agents/networks/critics.py
RL_OM/agents/processors/__init__.py
RL_OM/agents/processors/eoq_preprocessors.py
RL_OM/agents/processors/processors.py
RL_OM/agents/rl_agents/__init__.py
RL_OM/agents/rl_agents/sac_discrete.py
RL_OM/agents/rl_agents/sac_gumbel.py
RL_OM/agents/rl_agents/sac_hybrid.py
RL_OM/agents/rl_agents/sac_hybrid_reversed.py
RL_OM/agents/rl_agents/sac_hybrid_separate.py
RL_OM/agents/rl_agents/algorithms/__init__.py
RL_OM/agents/rl_agents/algorithms/sac_discrete.py
RL_OM/agents/rl_agents/algorithms/sac_gumbel.py
RL_OM/agents/rl_agents/algorithms/sac_hybrid.py
RL_OM/agents/rl_agents/algorithms/sac_hybrid_reversed.py
RL_OM/agents/rl_agents/algorithms/sac_hybrid_separate.py
RL_OM/agents/rl_agents/pre_specified_agents/PPO_classic.py
RL_OM/agents/rl_agents/pre_specified_agents/SAC_RNN.py
RL_OM/agents/rl_agents/pre_specified_agents/SAC_classic.py
RL_OM/agents/rl_agents/pre_specified_agents/SAC_discrete.py
RL_OM/agents/rl_agents/pre_specified_agents/SAC_gumbel.py
RL_OM/agents/rl_agents/pre_specified_agents/SAC_hybrid_gumbel.py
RL_OM/agents/rl_agents/pre_specified_agents/SAC_hybrid_naive.py
RL_OM-0.7.115.dist-info/LICENSE
RL_OM-0.7.115.dist-info/METADATA
RL_OM-0.7.115.dist-info/WHEEL
RL_OM-0.7.115.dist-info/entry_points.txt
RL_OM-0.7.115.dist-info/top_level.txt
RL_OM-0.7.115.dist-info/RECORD
