Metadata-Version: 2.1
Name: RL-OM
Version: 0.7.115
Summary: Reinforcement Learning Applications in Operations Management
Home-page: https://github.com/majoma7/RL_OM
Author: Magnus Maichle
Author-email: magnus.maichle@uni-wuerzburg.de
License: Apache Software License 2.0
Keywords: nbdev jupyter notebook python
Classifier: Development Status :: 4 - Beta
Classifier: Intended Audience :: Developers
Classifier: Natural Language :: English
Classifier: Programming Language :: Python :: 3.7
Classifier: Programming Language :: Python :: 3.8
Classifier: Programming Language :: Python :: 3.9
Classifier: Programming Language :: Python :: 3.10
Classifier: License :: OSI Approved :: Apache Software License
Requires-Python: >=3.7
License-File: LICENSE
Requires-Dist: numpy
Requires-Dist: mushroom-rl
Provides-Extra: dev
